spart_prompt/__init__.py
spart_prompt/evaluator.py
spart_prompt/external_llm_connector.py
spart_prompt/llm_connector.py
spart_prompt/local_llm_connector.py
spart_prompt/optimizer.py
spart_prompt/recommender.py
spart_prompt-1.0.0.dist-info/METADATA
spart_prompt-1.0.0.dist-info/WHEEL
spart_prompt-1.0.0.dist-info/top_level.txt
spart_prompt-1.0.0.dist-info/RECORD
