Metadata-Version: 2.4
Name: spart-prompt
Version: 1.0.0
Summary: Streamlined Prompt Automation and Recommender Tool (SPART): A Prompt Recommender System for Accurate Content Generation
Author-email: Faiz Aziz <faizazizatk@gmail.com>
License: MIT
Project-URL: Repository, https://github.com/FaizAzizAtK/SPART
Requires-Python: >=3.7
Requires-Dist: numpy==2.2.5
Requires-Dist: sentence-transformers==4.1.0
Requires-Dist: rouge-score==0.1.2
Requires-Dist: langchain==0.3.24
Requires-Dist: langchain-community==0.3.22
Requires-Dist: langchain-openai==0.3.14
Requires-Dist: transformers==4.51.3
Requires-Dist: pandas==2.2.3
Requires-Dist: pytest==8.3.5
